<?xml version = '1.0' encoding = 'UTF-8'?>
<Relation class="oracle.dbtools.crest.model.design.logical.Relation" name="Fisa_afectiune_FK" directorySegmentName="seg_0" id="4262B450-5CBE-BE20-63E1-FC29AD10EA70">
<createdBy>boaca</createdBy>
<createdTime>2022-10-26 17:07:09 UTC</createdTime>
<ownerDesignName>BDP</ownerDesignName>
<engineerTo>
<item key="E7EA04A8-633F-C37A-9ACC-63C5FF776C90" value="true"/>
</engineerTo>
<identifying>false</identifying>
<nameOnSource>are </nameOnSource>
<nameOnTarget>sunt in</nameOnTarget>
<optionalSource>false</optionalSource>
<optionalTarget>true</optionalTarget>
<sourceCardinality>*</sourceCardinality>
<sourceEntity>331BB2F1-05A2-8372-00F1-D22008006ABF</sourceEntity>
<targetCardinalityString>*</targetCardinalityString>
<targetEntity>AFC9ED59-DB50-29B3-27FE-4EB3DCED6119</targetEntity>
<transferable>true</transferable>
<deleteRule>NO ACTION</deleteRule>
</Relation>